dine/__init__.py
dine/api.py
dine/cli.py
dine/py.typed
dine-0.0.2.dist-info/METADATA
dine-0.0.2.dist-info/WHEEL
dine-0.0.2.dist-info/entry_points.txt
dine-0.0.2.dist-info/licenses/LICENSE
dine-0.0.2.dist-info/RECORD
