Metadata-Version: 2.4
Name: dine
Version: 0.0.2
Summary: Librería y línea de comandos para explorar y exportar datos del Instituto Nacional de Estadística de España
Author-email: David Gasquez <davidgasquez@gmail.com>
License-File: LICENSE
Requires-Python: >=3.13.2
Requires-Dist: httpx>=0.28.1
Requires-Dist: polars>=1.24.0
Requires-Dist: typer>=0.15.2
